scDenorm/__init__.py
scDenorm/_modidx.py
scDenorm/core.py
scDenorm/denorm.py
scDenorm-1.0.1.dist-info/LICENSE
scDenorm-1.0.1.dist-info/METADATA
scDenorm-1.0.1.dist-info/WHEEL
scDenorm-1.0.1.dist-info/entry_points.txt
scDenorm-1.0.1.dist-info/top_level.txt
scDenorm-1.0.1.dist-info/RECORD
