Metadata-Version: 2.1
Name: scDenorm
Version: 1.0.1
Summary: scDenorm: a denormalization tool for single-cell transcriptomics data
Home-page: https://github.com/changebio/scDenorm
Author: Yin Huang
Author-email: changebio@yeah.net
License: Apache Software License 2.0
Keywords: nbdev jupyter notebook python
Platform: UNKNOWN
Classifier: Development Status :: 4 - Beta
Classifier: Intended Audience :: Developers
Classifier: Natural Language :: English
Classifier: Programming Language :: Python :: 3.7
Classifier: Programming Language :: Python :: 3.8
Classifier: Programming Language :: Python :: 3.9
Classifier: Programming Language :: Python :: 3.10
Classifier: License :: OSI Approved :: Apache Software License
Requires-Python: >=3.7
License-File: LICENSE
Requires-Dist: numpy
Requires-Dist: pandas
Requires-Dist: matplotlib
Requires-Dist: scanpy
Requires-Dist: anndata
Requires-Dist: scipy
Requires-Dist: tqdm
Requires-Dist: pathlib
Requires-Dist: fastcore
Requires-Dist: colorlog
Provides-Extra: dev
